<DOMSymbolItem xmlns:xsi="http://www.w3.org/2001/XMLSchema-instance" xmlns="http://ns.adobe.com/xfl/2008/" name="cta-amit" itemID="4f33017c-00000682" lastModified="1328743928">
  <timeline>
    <DOMTimeline name="cta-amit">
      <layers>
        <DOMLayer name="Layer 1" color="#4FFF4F" current="true" isSelected="true">
          <frames>
            <DOMFrame index="0" keyMode="9728">
              <elements>
                <DOMGroup>
                  <members>
                    <DOMBitmapInstance libraryItemName="numby_CTA.psd Assets/iPad">
                      <matrix>
                        <Matrix tx="-43" ty="-77"/>
                      </matrix>
                    </DOMBitmapInstance>
                  </members>
                </DOMGroup>
                <DOMStaticText width="97.5" height="42.8" isSelectable="false">
                  <matrix>
                    <Matrix tx="-48.5" ty="56.75"/>
                  </matrix>
                  <textRuns>
                    <DOMTextRun>
                      <characters>Get Numby&#xD;for iPad</characters>
                      <textAttrs>
                        <DOMTextAttrs alignment="center" aliasText="false" size="17" bitmapSize="340" face="ChaparralPro-Regular" fillColor="#FFFFFF"/>
                      </textAttrs>
                    </DOMTextRun>
                  </textRuns>
                </DOMStaticText>
              </elements>
            </DOMFrame>
          </frames>
        </DOMLayer>
      </layers>
    </DOMTimeline>
  </timeline>
</DOMSymbolItem>